LICENSE
MANIFEST.in
README.md
requirements.txt
setup.py
eave/__init__.py
eave/eave.py
eave/template.html
eave/utils.py
eave.egg-info/PKG-INFO
eave.egg-info/SOURCES.txt
eave.egg-info/dependency_links.txt
eave.egg-info/requires.txt
eave.egg-info/top_level.txt
eave/resource/best.png
eave/resource/best1.png
eave/resource/false.svg
eave/resource/logo.jpg
eave/resource/style.css
eave/resource/style.origin.css
eave/resource/templateorigin.html
eave/resource/true.svg
eave/resource/highlight/highlight.pack.js
eave/resource/highlight/styles/a11y-dark.css
eave/resource/highlight/styles/a11y-light.css
eave/resource/highlight/styles/agate.css
eave/resource/highlight/styles/an-old-hope.css
eave/resource/highlight/styles/androidstudio.css
eave/resource/highlight/styles/arduino-light.css
eave/resource/highlight/styles/arta.css
eave/resource/highlight/styles/ascetic.css
eave/resource/highlight/styles/atelier-cave-dark.css
eave/resource/highlight/styles/atelier-cave-light.css
eave/resource/highlight/styles/atelier-dune-dark.css
eave/resource/highlight/styles/atelier-dune-light.css
eave/resource/highlight/styles/atelier-estuary-dark.css
eave/resource/highlight/styles/atelier-estuary-light.css
eave/resource/highlight/styles/atelier-forest-dark.css
eave/resource/highlight/styles/atelier-forest-light.css
eave/resource/highlight/styles/atelier-heath-dark.css
eave/resource/highlight/styles/atelier-heath-light.css
eave/resource/highlight/styles/atelier-lakeside-dark.css
eave/resource/highlight/styles/atelier-lakeside-light.css
eave/resource/highlight/styles/atelier-plateau-dark.css
eave/resource/highlight/styles/atelier-plateau-light.css
eave/resource/highlight/styles/atelier-savanna-dark.css
eave/resource/highlight/styles/atelier-savanna-light.css
eave/resource/highlight/styles/atelier-seaside-dark.css
eave/resource/highlight/styles/atelier-seaside-light.css
eave/resource/highlight/styles/atelier-sulphurpool-dark.css
eave/resource/highlight/styles/atelier-sulphurpool-light.css
eave/resource/highlight/styles/atom-one-dark-reasonable.css
eave/resource/highlight/styles/atom-one-dark.css
