Metadata-Version: 2.1
Name: eave
Version: 0.1.1
Summary: A Restful Api Document Builder For Pythonista
Home-page: https://github.com/taojy123/eave
Author: tao.py
Author-email: taojy123@163.com
Maintainer: tao.py
Maintainer-email: taojy123@163.com
License: MIT License
Platform: all
Classifier: Programming Language :: Python
Classifier: Programming Language :: Python :: Implementation
Classifier: Programming Language :: Python :: 3
Classifier: Topic :: Software Development :: Libraries
